[
    {
        "title": "行为验证",
        "url": "https://www.douyin.com/video/7560630515041078579",
        "time": "2025-10-14 15:30:00",
        "cover": "https://p3-pc-sign.douyinpic.com/obj/tos-cn-i-dy/16e06d7ab945455abd7d8380aeb789dd?lk3s=138a59ce&x-expires=1762261200&x-signature=LVSFeMOIkoyezCmrLmznlFHML2Y%3D&from=327834062_large&s=PackSourceEnum_PUBLISH&se=false&sc=dynamic_cover&biz_tag=pcweb_cover&l=202510212109571D355A1A9D38691A8923"
    },
    {
        "title": "单点登录的模式",
        "url": "https://www.douyin.com/video/7559940239066746146",
        "time": "2025-10-13 15:30:00",
        "cover": "https://p3-pc-sign.douyinpic.com/obj/tos-cn-i-dy/8f4bf273f7364329ae7069cb213e7801?lk3s=138a59ce&x-expires=1762261200&x-signature=sBPL3mc2y2FyQCrFAAZmu1cLqfI%3D&from=327834062_large&s=PackSourceEnum_PUBLISH&se=false&sc=dynamic_cover&biz_tag=pcweb_cover&l=202510212109571D355A1A9D38691A8923"
    },
    {
        "title": "可缓存的方法",
        "url": "https://www.douyin.com/video/7559514412361452850",
        "time": "2025-10-11 15:30:00",
        "cover": "https://p9-pc-sign.douyinpic.com/obj/tos-cn-i-dy/a463b0d6750b4f6f8893c04f8adfa015?lk3s=138a59ce&x-expires=1762261200&x-signature=THxg3ceWozrGORan7QmEZRYnHug%3D&from=327834062_large&s=PackSourceEnum_PUBLISH&se=false&sc=dynamic_cover&biz_tag=pcweb_cover&l=202510212109571D355A1A9D38691A8923"
    },
    {
        "title": "Web性能指标",
        "url": "https://www.douyin.com/video/7559505198406765862",
        "time": "2025-10-10 16:21:06",
        "cover": "https://p3-pc-sign.douyinpic.com/obj/tos-cn-i-dy/55eb52a81d1545f58d7610c234575ad5?lk3s=138a59ce&x-expires=1762261200&x-signature=5vPHWoXhdkkl7fbPh8D0f7ODXoE%3D&from=327834062_large&s=PackSourceEnum_PUBLISH&se=false&sc=dynamic_cover&biz_tag=pcweb_cover&l=202510212109571D355A1A9D38691A8923"
    },
    {
        "title": "打印对象的「BUG」",
        "url": "https://www.douyin.com/video/7555431759739997475",
        "time": "2025-10-09 15:30:00",
        "cover": "https://p3-pc-sign.douyinpic.com/obj/tos-cn-i-dy/eefc99760d614289874d6d85420d0484?lk3s=138a59ce&x-expires=1762261200&x-signature=jwpRc0vkvYxyQEBiPX2LHlu%2FSfM%3D&from=327834062_large&s=PackSourceEnum_PUBLISH&se=false&sc=dynamic_cover&biz_tag=pcweb_cover&l=202510212109571D355A1A9D38691A8923"
    },
    {
        "title": "最优解问题的典型思路",
        "url": "https://www.douyin.com/video/7555430983391038772",
        "time": "2025-10-08 15:30:00",
        "cover": "https://p3-pc-sign.douyinpic.com/obj/tos-cn-i-dy/d1cc12d4857441ca800e8df25653b9e6?lk3s=138a59ce&x-expires=1762261200&x-signature=7maOLkbW7XDoVGFRX8rJzKoZwSg%3D&from=327834062_large&s=PackSourceEnum_PUBLISH&se=false&sc=dynamic_cover&biz_tag=pcweb_cover&l=202510212109571D355A1A9D38691A8923"
    },
    {
        "title": "多行文本擦除效果",
        "url": "https://www.douyin.com/video/7555430164524469504",
        "time": "2025-10-07 15:30:00",
        "cover": "https://p3-pc-sign.douyinpic.com/obj/tos-cn-i-dy/52545a0ff55941768403bc51a97ca1ee?lk3s=138a59ce&x-expires=1762261200&x-signature=8fMIRsqYRoX97HwDzmIaW3xGFDY%3D&from=327834062_large&s=PackSourceEnum_PUBLISH&se=false&sc=dynamic_cover&biz_tag=pcweb_cover&l=202510212109571D355A1A9D38691A8923"
    },
    {
        "title": "读取文件原始内容",
        "url": "https://www.douyin.com/video/7555429726815259956",
        "time": "2025-10-06 15:30:00",
        "cover": "https://p3-pc-sign.douyinpic.com/obj/tos-cn-i-dy/a4ed0e5c36c24c86bbe468b5f247d0b0?lk3s=138a59ce&x-expires=1762261200&x-signature=76OYLLXSREM5g59pg1eSNquhL0g%3D&from=327834062_large&s=PackSourceEnum_PUBLISH&se=false&sc=dynamic_cover&biz_tag=pcweb_cover&l=202510212109571D355A1A9D38691A8923"
    },
    {
        "title": "系统级取色器",
        "url": "https://www.douyin.com/video/7555428913527246132",
        "time": "2025-10-04 15:30:00",
        "cover": "https://p9-pc-sign.douyinpic.com/obj/tos-cn-i-dy/0e2c5e63e13045ae97ca67dc7311f9bb?lk3s=138a59ce&x-expires=1762261200&x-signature=tGwLtt8S9F4oaARM0lj1%2FzOeW7Q%3D&from=327834062_large&s=PackSourceEnum_PUBLISH&se=false&sc=dynamic_cover&biz_tag=pcweb_cover&l=202510212109571D355A1A9D38691A8923"
    },
    {
        "title": "Promise面试题",
        "url": "https://www.douyin.com/video/7555428501763935488",
        "time": "2025-10-03 15:30:00",
        "cover": "https://p3-pc-sign.douyinpic.com/obj/tos-cn-i-dy/578e074d69be45f0a76b04a845e9befd?lk3s=138a59ce&x-expires=1762261200&x-signature=rhXH2s0O8ZH%2FpgE329X5PBK01w8%3D&from=327834062_large&s=PackSourceEnum_PUBLISH&se=false&sc=dynamic_cover&biz_tag=pcweb_cover&l=202510212109571D355A1A9D38691A8923"
    },
    {
        "title": "实现私有字段",
        "url": "https://www.douyin.com/video/7555428078525173032",
        "time": "2025-10-02 15:30:00",
        "cover": "https://p3-pc-sign.douyinpic.com/obj/tos-cn-i-dy/a8b0ea42717945b8a5093fd263757e9f?lk3s=138a59ce&x-expires=1762261200&x-signature=BixLbE3vt4MVVe81zkrIHJmNwJU%3D&from=327834062_large&s=PackSourceEnum_PUBLISH&se=false&sc=dynamic_cover&biz_tag=pcweb_cover&l=202510212109571D355A1A9D38691A8923"
    },
    {
        "title": "阿里云的文件上传",
        "url": "https://www.douyin.com/video/7555427186593778978",
        "time": "2025-10-01 15:30:00",
        "cover": "https://p3-pc-sign.douyinpic.com/obj/tos-cn-i-dy/09f87fce6f8d4b28a079c496da7c74c8?lk3s=138a59ce&x-expires=1762261200&x-signature=Oq94Zz7HfE9E1%2FCDCEpUkgF465c%3D&from=327834062_large&s=PackSourceEnum_PUBLISH&se=false&sc=dynamic_cover&biz_tag=pcweb_cover&l=202510212109571D355A1A9D38691A8923"
    },
    {
        "title": "判断稀疏数组",
        "url": "https://www.douyin.com/video/7555426720167955747",
        "time": "2025-09-30 15:30:00",
        "cover": "https://p9-pc-sign.douyinpic.com/obj/tos-cn-i-dy/61909ea6c83b48379a7da7cf2320e77a?lk3s=138a59ce&x-expires=1762261200&x-signature=4CSZOJHipI1%2FFu4flB%2B55M9Xyzk%3D&from=327834062_large&s=PackSourceEnum_PUBLISH&se=false&sc=dynamic_cover&biz_tag=pcweb_cover&l=202510212109571D355A1A9D38691A8923"
    },
    {
        "title": "统一vite中的图片转换逻辑",
        "url": "https://www.douyin.com/video/7555422586646269210",
        "time": "2025-09-29 16:18:29",
        "cover": "https://p3-pc-sign.douyinpic.com/obj/tos-cn-i-dy/c572e8e4790c4b3e8706bedf4b554679?lk3s=138a59ce&x-expires=1762261200&x-signature=X2KIJsQmP6WO62UqtYwyrYgQAR0%3D&from=327834062_large&s=PackSourceEnum_PUBLISH&se=false&sc=dynamic_cover&biz_tag=pcweb_cover&l=202510212109571D355A1A9D38691A8923"
    },
    {
        "title": "最近距离排序",
        "url": "https://www.douyin.com/video/7554692035094072603",
        "time": "2025-09-27 17:03:34",
        "cover": "https://p3-pc-sign.douyinpic.com/obj/tos-cn-i-dy/4a7fe39480784ee492c2345cc3e96176?lk3s=138a59ce&x-expires=1762261200&x-signature=dAievjhiNmPSoQK%2BJUyCG4xdFpQ%3D&from=327834062_large&s=PackSourceEnum_PUBLISH&se=false&sc=dynamic_cover&biz_tag=pcweb_cover&l=202510212109571D355A1A9D38691A8923"
    },
    {
        "title": "动态执行JS",
        "url": "https://www.douyin.com/video/7554322444165582118",
        "time": "2025-09-26 17:09:20",
        "cover": "https://p3-pc-sign.douyinpic.com/obj/tos-cn-i-dy/c1f245e6505f4583af13e3f3979a3a72?lk3s=138a59ce&x-expires=1762261200&x-signature=KXe%2FbnNZJVSAnCskchSyV%2B6ElRg%3D&from=327834062_large&s=PackSourceEnum_PUBLISH&se=false&sc=dynamic_cover&biz_tag=pcweb_cover&l=202510212109571D355A1A9D38691A8923"
    },
    {
        "title": "大文件分片",
        "url": "https://www.douyin.com/video/7553951574670757129",
        "time": "2025-09-25 17:10:12",
        "cover": "https://p3-pc-sign.douyinpic.com/obj/tos-cn-i-dy/00b8980821f147619540d1d2c3053d39?lk3s=138a59ce&x-expires=1762261200&x-signature=2HEA1aA9GHf%2B2pizuy3KjiI3RCE%3D&from=327834062_large&s=PackSourceEnum_PUBLISH&se=false&sc=dynamic_cover&biz_tag=pcweb_cover&l=202510212109571D355A1A9D38691A8923"
    },
    {
        "title": "srcset和sizes",
        "url": "https://www.douyin.com/video/7553260616409025807",
        "time": "2025-09-24 15:30:00",
        "cover": "https://p3-pc-sign.douyinpic.com/obj/tos-cn-i-dy/13da09729bea40f9b66eac5d6a9507db?lk3s=138a59ce&x-expires=1762261200&x-signature=q%2FfdS%2BdiZCIvT3I6CrJqBQkQNDM%3D&from=327834062_large&s=PackSourceEnum_PUBLISH&se=false&sc=dynamic_cover&biz_tag=pcweb_cover&l=202510212109571D355A1A9D38691A8923"
    },
    {
        "title": "手动解析DOM树",
        "url": "https://www.douyin.com/video/7552832338447633707",
        "time": "2025-09-23 15:30:00",
        "cover": "https://p3-pc-sign.douyinpic.com/obj/tos-cn-i-dy/d98c3b9cd195437f81fb77c4b2e99469?lk3s=138a59ce&x-expires=1762261200&x-signature=znGZI8zMIlMyrNg11B%2FcpUyXM3I%3D&from=327834062_large&s=PackSourceEnum_PUBLISH&se=false&sc=dynamic_cover&biz_tag=pcweb_cover&l=202510212109571D355A1A9D38691A8923"
    },
    {
        "title": "组件级权限控制的最佳实践",
        "url": "https://www.douyin.com/video/7552086653322530082",
        "time": "2025-09-22 15:30:00",
        "cover": "https://p9-pc-sign.douyinpic.com/obj/tos-cn-i-dy/4af09fca83154b1ead59dd4ec3e3fe63?lk3s=138a59ce&x-expires=1762261200&x-signature=YyAtra9b5n4nA9k6EIqHDkhIX6w%3D&from=327834062_large&s=PackSourceEnum_PUBLISH&se=false&sc=dynamic_cover&biz_tag=pcweb_cover&l=202510212109571D355A1A9D38691A8923"
    }
]
