[
    { "title": "浏览器原生弹窗", "url": "https://www.douyin.com/video/7582141836622384438", "time": "2025-12-11 15:30:00", "cover": "https://p3-pc-sign.douyinpic.com/obj/tos-cn-i-dy/576c222c15184b4d8e39bfab7e8cd76e?lk3s=138a59ce&x-expires=1767272400&x-signature=Oi%2FvjBjlyIwj%2B6B%2ByqoYMJLuclY%3D&from=327834062_large&s=PackSourceEnum_PUBLISH&se=false&sc=dynamic_cover&biz_tag=pcweb_cover&l=202512182112268EDA3AD71363FF1A62AC" },
    { "title": "利用延迟实现复杂动画", "url": "https://www.douyin.com/video/7581837566610115894", "time": "2025-12-10 15:30:00", "cover": "https://p3-pc-sign.douyinpic.com/obj/tos-cn-i-dy/66435f360f4d48bf863a87a55e171959?lk3s=138a59ce&x-expires=1767272400&x-signature=JPo4zzj%2FDALhC4fkHk%2FyRXX302s%3D&from=327834062_large&s=PackSourceEnum_PUBLISH&se=false&sc=dynamic_cover&biz_tag=pcweb_cover&l=202512182112268EDA3AD71363FF1A62AC" },
    { "title": "Sass实现文字替换", "url": "https://www.douyin.com/video/7581410394434997544", "time": "2025-12-09 15:30:00", "cover": "https://p3-pc-sign.douyinpic.com/obj/tos-cn-i-dy/a6046b21db46434d8bd6c0b4e2067cec?lk3s=138a59ce&x-expires=1767272400&x-signature=0K0VHEGgU8m9qVXxIafxlDQd4zs%3D&from=327834062_large&s=PackSourceEnum_PUBLISH&se=false&sc=dynamic_cover&biz_tag=pcweb_cover&l=202512182112268EDA3AD71363FF1A62AC" },
    { "title": "俄罗斯方块实现思路", "url": "https://www.douyin.com/video/7580718176103681322", "time": "2025-12-08 15:30:00", "cover": "https://p3-pc-sign.douyinpic.com/obj/tos-cn-i-dy/fe45670897ba412ea587ce5cf35c97e6?lk3s=138a59ce&x-expires=1767272400&x-signature=tP6pMAuF8d5nFe6DoIQJSeCEstI%3D&from=327834062_large&s=PackSourceEnum_PUBLISH&se=false&sc=dynamic_cover&biz_tag=pcweb_cover&l=202512182112268EDA3AD71363FF1A62AC" },
    { "title": "使用SASS实现主题切换", "url": "https://www.douyin.com/video/7580300809468939560", "time": "2025-12-06 15:30:00", "cover": "https://p3-pc-sign.douyinpic.com/obj/tos-cn-i-dy/2013d07afb6a4bd2a1b48b823b345cce?lk3s=138a59ce&x-expires=1767272400&x-signature=djXtPQcUl19ZnwZkJo1uOpWlNZ4%3D&from=327834062_large&s=PackSourceEnum_PUBLISH&se=false&sc=dynamic_cover&biz_tag=pcweb_cover&l=202512182112268EDA3AD71363FF1A62AC" },
    { "title": "无限视差滚动", "url": "https://www.douyin.com/video/7580297557851622708", "time": "2025-12-05 17:06:08", "cover": "https://p3-pc-sign.douyinpic.com/obj/tos-cn-i-dy/d47049784ef54533bee57b0d4aa0bef3?lk3s=138a59ce&x-expires=1767272400&x-signature=gG8eyW%2B0fn0aKyNr7zQm2sMdIKk%3D&from=327834062_large&s=PackSourceEnum_PUBLISH&se=false&sc=dynamic_cover&biz_tag=pcweb_cover&l=202512182112268EDA3AD71363FF1A62AC" },
    { "title": "漂亮的文字阴影", "url": "https://www.douyin.com/video/7579611081631468843", "time": "2025-12-04 15:30:00", "cover": "https://p3-pc-sign.douyinpic.com/obj/tos-cn-i-dy/45634ebed0084248bf0ed5870c2c7e70?lk3s=138a59ce&x-expires=1767272400&x-signature=WLAV6nzeyuTE%2B7Vj8YTW4Flccjw%3D&from=327834062_large&s=PackSourceEnum_PUBLISH&se=false&sc=dynamic_cover&biz_tag=pcweb_cover&l=202512182112268EDA3AD71363FF1A62AC" },
    { "title": "无法预测的大数运算", "url": "https://www.douyin.com/video/7579183143404457266", "time": "2025-12-03 15:30:00", "cover": "https://p3-pc-sign.douyinpic.com/obj/tos-cn-i-dy/7cea0584285647388dd82da0e3cd6e2e?lk3s=138a59ce&x-expires=1767272400&x-signature=XWYA8ETHjbpxuexy8PdAiZZLQIY%3D&from=327834062_large&s=PackSourceEnum_PUBLISH&se=false&sc=dynamic_cover&biz_tag=pcweb_cover&l=202512182112268EDA3AD71363FF1A62AC" },
    { "title": "无法取消的默认行为", "url": "https://www.douyin.com/video/7579198392413310251", "time": "2025-12-02 18:00:52", "cover": "https://p3-pc-sign.douyinpic.com/obj/tos-cn-i-dy/b4e20aec7c93441ba75a80745aae296f?lk3s=138a59ce&x-expires=1767272400&x-signature=65%2B2k93JC7Crsst29QWBXR2pd3w%3D&from=327834062_large&s=PackSourceEnum_PUBLISH&se=false&sc=dynamic_cover&biz_tag=pcweb_cover&l=202512182112268EDA3AD71363FF1A62AC" },
    { "title": "鼠标和键盘事件的常见问题", "url": "https://www.douyin.com/video/7577690044861844745", "time": "2025-12-01 15:30:00", "cover": "https://p3-pc-sign.douyinpic.com/obj/tos-cn-i-dy/3488731f77304ec383e96af6083572c7?lk3s=138a59ce&x-expires=1767272400&x-signature=Rcb9jYGRywCL4S1D6OvTGi1XrQI%3D&from=327834062_large&s=PackSourceEnum_PUBLISH&se=false&sc=dynamic_cover&biz_tag=pcweb_cover&l=202512182112268EDA3AD71363FF1A62AC" },
    { "title": "如何防截屏防录制", "url": "https://www.douyin.com/video/7577689354382871818", "time": "2025-11-29 15:30:00", "cover": "https://p3-pc-sign.douyinpic.com/obj/tos-cn-i-dy/2411d5174d6341e084cd61cc1a2ddf86?lk3s=138a59ce&x-expires=1767272400&x-signature=OBx6g4Ow8QUslLNBhBGKQeKfPsw%3D&from=327834062_large&s=PackSourceEnum_PUBLISH&se=false&sc=dynamic_cover&biz_tag=pcweb_cover&l=202512182112268EDA3AD71363FF1A62AC" },
    { "title": "Ajax中的各种常见概念", "url": "https://www.douyin.com/video/7577369688749935918", "time": "2025-11-28 15:30:00", "cover": "https://p3-pc-sign.douyinpic.com/obj/tos-cn-i-dy/af05167bf03d481699e87b3946e86f9f?lk3s=138a59ce&x-expires=1767272400&x-signature=E%2BU1aEkB6cABDe6NK2I6smggCR8%3D&from=327834062_large&s=PackSourceEnum_PUBLISH&se=false&sc=dynamic_cover&biz_tag=pcweb_cover&l=202512182112268EDA3AD71363FF1A62AC" },
    { "title": "copy的监听和解禁", "url": "https://www.douyin.com/video/7576950585681923382", "time": "2025-11-27 15:30:00", "cover": "https://p3-pc-sign.douyinpic.com/obj/tos-cn-i-dy/2b83f22f08664de8b91794ed669fd126?lk3s=138a59ce&x-expires=1767272400&x-signature=fXx59eWKk9ky2nJqkTfm7dMT704%3D&from=327834062_large&s=PackSourceEnum_PUBLISH&se=false&sc=dynamic_cover&biz_tag=pcweb_cover&l=202512182112268EDA3AD71363FF1A62AC" },
    { "title": "黏性定位", "url": "https://www.douyin.com/video/7576633656769301811", "time": "2025-11-26 15:30:00", "cover": "https://p3-pc-sign.douyinpic.com/obj/tos-cn-i-dy/16b30363cc9f47c192276acfa390e769?lk3s=138a59ce&x-expires=1767272400&x-signature=xka9jVmRHiZUPCUB6LpVe0IVr1U%3D&from=327834062_large&s=PackSourceEnum_PUBLISH&se=false&sc=dynamic_cover&biz_tag=pcweb_cover&l=202512182112268EDA3AD71363FF1A62AC" },
    { "title": "initial、unset、revert", "url": "https://www.douyin.com/video/7576215142829018404", "time": "2025-11-25 15:30:00", "cover": "https://p3-pc-sign.douyinpic.com/obj/tos-cn-i-dy/9e17e16d9d544bcfae8e53b7efe00e72?lk3s=138a59ce&x-expires=1767272400&x-signature=pIvj%2FRl9K8xsQqxsgHkOQhFC95A%3D&from=327834062_large&s=PackSourceEnum_PUBLISH&se=false&sc=dynamic_cover&biz_tag=pcweb_cover&l=202512182112268EDA3AD71363FF1A62AC" },
    { "title": "用canvas玩转图片", "url": "https://www.douyin.com/video/7575475355868351807", "time": "2025-11-24 15:30:00", "cover": "https://p3-pc-sign.douyinpic.com/obj/tos-cn-i-dy/7c8b336d8849491b85cc06e70b02a905?lk3s=138a59ce&x-expires=1767272400&x-signature=pXNqld%2BpdRSDMI%2BDO7xuhTHNnXU%3D&from=327834062_large&s=PackSourceEnum_PUBLISH&se=false&sc=dynamic_cover&biz_tag=pcweb_cover&l=202512182112268EDA3AD71363FF1A62AC" },
    { "title": "Cookie中的SameSite", "url": "https://www.douyin.com/video/7575475971797667078", "time": "2025-11-22 17:15:54", "cover": "https://p3-pc-sign.douyinpic.com/obj/tos-cn-i-dy/678b6e0a084a49fdb925ba5ab32a9992?lk3s=138a59ce&x-expires=1767272400&x-signature=PMQ6WAUWMaJdontTY%2F0hUsBr5yQ%3D&from=327834062_large&s=PackSourceEnum_PUBLISH&se=false&sc=dynamic_cover&biz_tag=pcweb_cover&l=202512182112268EDA3AD71363FF1A62AC" },
    { "title": "实现防篡改的水印", "url": "https://www.douyin.com/video/7574728224660360454", "time": "2025-11-21 15:30:00", "cover": "https://p9-pc-sign.douyinpic.com/obj/tos-cn-i-dy/cd7fcbe65c3041c994bc7e37f27218d8?lk3s=138a59ce&x-expires=1767272400&x-signature=8pQov93o%2FFV9ZR%2BpjXPApnRTAUg%3D&from=327834062_large&s=PackSourceEnum_PUBLISH&se=false&sc=dynamic_cover&biz_tag=pcweb_cover&l=202512182112268EDA3AD71363FF1A62AC" },
    { "title": "钉钉官网的滚动动画", "url": "https://www.douyin.com/video/7574417235104566547", "time": "2025-11-20 15:30:00", "cover": "https://p3-pc-sign.douyinpic.com/obj/tos-cn-i-dy/1bab4afdca6a44538876f44cce510d27?lk3s=138a59ce&x-expires=1767272400&x-signature=ySVedhEdy%2B%2FeUCJ%2BTUf7rwRbD%2Bo%3D&from=327834062_large&s=PackSourceEnum_PUBLISH&se=false&sc=dynamic_cover&biz_tag=pcweb_cover&l=202512182112268EDA3AD71363FF1A62AC" },
    { "title": "幻影依赖", "url": "https://www.douyin.com/video/7573993949443001636", "time": "2025-11-19 15:30:00", "cover": "https://p9-pc-sign.douyinpic.com/obj/tos-cn-i-dy/7a38c6623eb64de5bada59b32a2bd80f?lk3s=138a59ce&x-expires=1767272400&x-signature=ptnHYvfnO2Duz1Uyr0r5Z9dOfLE%3D&from=327834062_large&s=PackSourceEnum_PUBLISH&se=false&sc=dynamic_cover&biz_tag=pcweb_cover&l=202512182112268EDA3AD71363FF1A62AC" }
]
