[
    {
        "title": "数字格式化",
        "url": "https://www.douyin.com/video/7509748478923361546",
        "time": "2025-05-29 14:21:27",
        "cover": "https://p3-pc-sign.douyinpic.com/obj/tos-cn-i-dy/659179f7b4ee43a0814041c3858c3920?lk3s=138a59ce&x-expires=1749780000&x-signature=qGEE3u%2B9%2FzmPKfeSt0V0GpmaC1g%3D&from=327834062_large&s=PackSourceEnum_PUBLISH&se=false&sc=dynamic_cover&biz_tag=pcweb_cover&l=202505301020077256483EA44FDA42FB96"
    },
    {
        "title": "什么是Web API",
        "url": "https://www.douyin.com/video/7509115037387148559",
        "time": "2025-05-28 11:50:00",
        "cover": "https://p3-pc-sign.douyinpic.com/obj/tos-cn-i-dy/f6faee4fdc7b4927af374c6b8d4fc5c8?lk3s=138a59ce&x-expires=1749780000&x-signature=FTKu1UyEHw1gYpfspD6j52TOM4M%3D&from=327834062_large&s=PackSourceEnum_PUBLISH&se=false&sc=dynamic_cover&biz_tag=pcweb_cover&l=202505301020077256483EA44FDA42FB96"
    },
    {
        "title": "使用void 0 替换undefined",
        "url": "https://www.douyin.com/video/7508675187282382090",
        "time": "2025-05-27 11:50:00",
        "cover": "https://p3-pc-sign.douyinpic.com/obj/tos-cn-i-dy/de4820ef17a44c509f3cffa1b889f963?lk3s=138a59ce&x-expires=1749780000&x-signature=8ydxqM0rnv3%2F0W0Yp8PsuuzCpTc%3D&from=327834062_large&s=PackSourceEnum_PUBLISH&se=false&sc=dynamic_cover&biz_tag=pcweb_cover&l=202505301020077256483EA44FDA42FB96"
    },
    {
        "title": "canvas动画",
        "url": "https://www.douyin.com/video/7507964372753452340",
        "time": "2025-05-26 11:50:00",
        "cover": "https://p3-pc-sign.douyinpic.com/obj/tos-cn-i-dy/3320e90c2f8247ddbbb009b7d9a4c17b?lk3s=138a59ce&x-expires=1749780000&x-signature=NSnFkmFGFU5wxIsmyMOiQ8CwwCc%3D&from=327834062_large&s=PackSourceEnum_PUBLISH&se=false&sc=dynamic_cover&biz_tag=pcweb_cover&l=202505301020077256483EA44FDA42FB96"
    },
    {
        "title": "Promise.try",
        "url": "https://www.douyin.com/video/7507569422408682789",
        "time": "2025-05-24 11:50:00",
        "cover": "https://p3-pc-sign.douyinpic.com/obj/tos-cn-i-dy/2b4841ec802b4423becb119b64c8239c?lk3s=138a59ce&x-expires=1749780000&x-signature=%2Bmw9j30c0zYlPhtIHDrBsuebNss%3D&from=327834062_large&s=PackSourceEnum_PUBLISH&se=false&sc=dynamic_cover&biz_tag=pcweb_cover&l=202505301020077256483EA44FDA42FB96"
    },
    {
        "title": "制作简易地图",
        "url": "https://www.douyin.com/video/7507197362192796978",
        "time": "2025-05-23 11:50:00",
        "cover": "https://p3-pc-sign.douyinpic.com/obj/tos-cn-i-dy/816b487bae6449269df062f8b44ac37d?lk3s=138a59ce&x-expires=1749780000&x-signature=8ErHLZR%2BD%2FxSGcSHYlXu4%2BrWnVI%3D&from=327834062_large&s=PackSourceEnum_PUBLISH&se=false&sc=dynamic_cover&biz_tag=pcweb_cover&l=202505301020077256483EA44FDA42FB96"
    },
    {
        "title": "渐进式图片",
        "url": "https://www.douyin.com/video/7506912720155970850",
        "time": "2025-05-22 11:50:00",
        "cover": "https://p3-pc-sign.douyinpic.com/obj/tos-cn-i-dy/6c1fe71826a24a339a7d6a7d36d6aa06?lk3s=138a59ce&x-expires=1749780000&x-signature=As%2FlfcJYOKhfeLSmJtRwDFSSuIQ%3D&from=327834062_large&s=PackSourceEnum_PUBLISH&se=false&sc=dynamic_cover&biz_tag=pcweb_cover&l=202505301020077256483EA44FDA42FB96"
    },
    {
        "title": "NProgress插件",
        "url": "https://www.douyin.com/video/7506453395234934028",
        "time": "2025-05-21 11:50:00",
        "cover": "https://p3-pc-sign.douyinpic.com/obj/tos-cn-i-dy/4fd4fec1c50e49999bb2939d14856645?lk3s=138a59ce&x-expires=1749780000&x-signature=H0vR60mhIDRGGubNKbfR22fCU%2FQ%3D&from=327834062_large&s=PackSourceEnum_PUBLISH&se=false&sc=dynamic_cover&biz_tag=pcweb_cover&l=202505301020077256483EA44FDA42FB96"
    },
    {
        "title": "拖拽排序",
        "url": "https://www.douyin.com/video/7506178687897734435",
        "time": "2025-05-20 11:50:00",
        "cover": "https://p3-pc-sign.douyinpic.com/obj/tos-cn-i-dy/354934071dc94b6cb562d952a879d259?lk3s=138a59ce&x-expires=1749780000&x-signature=V4ZdWtNG71%2Bqt9yY8nZpdz4LPms%3D&from=327834062_large&s=PackSourceEnum_PUBLISH&se=false&sc=dynamic_cover&biz_tag=pcweb_cover&l=202505301020077256483EA44FDA42FB96"
    },
    {
        "title": "统一vite中的图片转换逻辑",
        "url": "https://www.douyin.com/video/7504967565739920651",
        "time": "2025-05-19 11:50:00",
        "cover": "https://p3-pc-sign.douyinpic.com/obj/tos-cn-i-dy/853ad49f404d4ebc9cd08e467fc4adfa?lk3s=138a59ce&x-expires=1749780000&x-signature=N9Vn4PIzyaXDr9W%2FsfxQCTvoBhw%3D&from=327834062_large&s=PackSourceEnum_PUBLISH&se=false&sc=dynamic_cover&biz_tag=pcweb_cover&l=202505301020077256483EA44FDA42FB96"
    },
    {
        "title": "唤起本地应用",
        "url": "https://www.douyin.com/video/7504967268804381964",
        "time": "2025-05-17 11:50:00",
        "cover": "https://p3-pc-sign.douyinpic.com/obj/tos-cn-i-dy/209a2b97f3464aa8a3658249fd297b27?lk3s=138a59ce&x-expires=1749780000&x-signature=k4NhNBHVGWDCANjuKHTAh92GSRo%3D&from=327834062_large&s=PackSourceEnum_PUBLISH&se=false&sc=dynamic_cover&biz_tag=pcweb_cover&l=202505301020077256483EA44FDA42FB96"
    },
    {
        "title": "call和apply的链式调用",
        "url": "https://www.douyin.com/video/7504688698856885538",
        "time": "2025-05-16 11:50:00",
        "cover": "https://p3-pc-sign.douyinpic.com/obj/tos-cn-i-dy/59603699696f4f1db684faaa87850343?lk3s=138a59ce&x-expires=1749780000&x-signature=pHwPslsJgN0JES9YnzWIMrcwza8%3D&from=327834062_large&s=PackSourceEnum_PUBLISH&se=false&sc=dynamic_cover&biz_tag=pcweb_cover&l=202505301020077256483EA44FDA42FB96"
    },
    {
        "title": "弹性盒均分布局",
        "url": "https://www.douyin.com/video/7504220210656726326",
        "time": "2025-05-15 11:50:00",
        "cover": "https://p3-pc-sign.douyinpic.com/obj/tos-cn-i-dy/892283473ac9415eabdab6adab2f7d42?lk3s=138a59ce&x-expires=1749780000&x-signature=AzoMCINqzMyTQhYwDJSY7dbtpoU%3D&from=327834062_large&s=PackSourceEnum_PUBLISH&se=false&sc=dynamic_cover&biz_tag=pcweb_cover&l=202505301020077256483EA44FDA42FB96"
    },
    {
        "title": "让文字立起来",
        "url": "https://www.douyin.com/video/7503859361450708263",
        "time": "2025-05-14 11:50:00",
        "cover": "https://p3-pc-sign.douyinpic.com/obj/tos-cn-i-dy/42ef758a13ec4a8cb30fe21b8f95a534?lk3s=138a59ce&x-expires=1749780000&x-signature=SQsHP3e%2FU4bTXZHhvzj%2BAr4vj9M%3D&from=327834062_large&s=PackSourceEnum_PUBLISH&se=false&sc=dynamic_cover&biz_tag=pcweb_cover&l=202505301020077256483EA44FDA42FB96"
    },
    {
        "title": "图片裁剪上传原理",
        "url": "https://www.douyin.com/video/7503479886267354420",
        "time": "2025-05-13 11:50:00",
        "cover": "https://p3-pc-sign.douyinpic.com/obj/tos-cn-i-dy/68e70eb6d985415cb529074048876e4d?lk3s=138a59ce&x-expires=1749780000&x-signature=e1AyqOlJ%2Fp%2F23VYFtzJdbpl2GrI%3D&from=327834062_large&s=PackSourceEnum_PUBLISH&se=false&sc=dynamic_cover&biz_tag=pcweb_cover&l=202505301020077256483EA44FDA42FB96"
    },
    {
        "title": "闭包代码的提权漏洞",
        "url": "https://www.douyin.com/video/7502466755424488742",
        "time": "2025-05-12 11:50:00",
        "cover": "https://p3-pc-sign.douyinpic.com/obj/tos-cn-i-dy/a58debc179d04e12b9caed75cd9d7840?lk3s=138a59ce&x-expires=1749780000&x-signature=j%2FJUyersFd3YlJCkLWreMvO2wFs%3D&from=327834062_large&s=PackSourceEnum_PUBLISH&se=false&sc=dynamic_cover&biz_tag=pcweb_cover&l=202505301020077256483EA44FDA42FB96"
    },
    {
        "title": "生成渐变背景小工具",
        "url": "https://www.douyin.com/video/7502465555656396083",
        "time": "2025-05-10 11:50:00",
        "cover": "https://p3-pc-sign.douyinpic.com/obj/tos-cn-i-dy/044cf69a18b64af9bc4e9a0bd399562f?lk3s=138a59ce&x-expires=1749780000&x-signature=05Y%2FyREziiGsr1lz9cyCs%2Fl0dyA%3D&from=327834062_large&s=PackSourceEnum_PUBLISH&se=false&sc=dynamic_cover&biz_tag=pcweb_cover&l=202505301020077256483EA44FDA42FB96"
    },
    {
        "title": "优化代码分支",
        "url": "https://www.douyin.com/video/7501999523640675599",
        "time": "2025-05-09 11:50:00",
        "cover": "https://p3-pc-sign.douyinpic.com/obj/tos-cn-i-dy/80007d148b39463f869a8fa3993a988b?lk3s=138a59ce&x-expires=1749780000&x-signature=EQ262CNeLS4CF7Zp3glCDuufKtI%3D&from=327834062_large&s=PackSourceEnum_PUBLISH&se=false&sc=dynamic_cover&biz_tag=pcweb_cover&l=202505301020077256483EA44FDA42FB96"
    },
    {
        "title": "阿里云的文件上传",
        "url": "https://www.douyin.com/video/7501700329872968986",
        "time": "2025-05-08 11:50:00",
        "cover": "https://p3-pc-sign.douyinpic.com/obj/tos-cn-i-dy/3d91f62c64ca4f309e650f0cb0d8bd66?lk3s=138a59ce&x-expires=1749780000&x-signature=neQXFZiojuyE0%2FFCYE7IYFKeiVw%3D&from=327834062_large&s=PackSourceEnum_PUBLISH&se=false&sc=dynamic_cover&biz_tag=pcweb_cover&l=202505301020077256483EA44FDA42FB96"
    },
    {
        "title": "copy的监听和解禁",
        "url": "https://www.douyin.com/video/7501252764991819058",
        "time": "2025-05-07 11:50:00",
        "cover": "https://p3-pc-sign.douyinpic.com/obj/tos-cn-i-dy/dca00e259a1d43f4937cb2de7451828f?lk3s=138a59ce&x-expires=1749780000&x-signature=TJ%2BxEpgefwgzcRHxVTLc8W8YDQE%3D&from=327834062_large&s=PackSourceEnum_PUBLISH&se=false&sc=dynamic_cover&biz_tag=pcweb_cover&l=202505301020077256483EA44FDA42FB96"
    }
]
